flokilum/__init__.py
flokilum/_mdx.py
flokilum/arch/__init__.py
flokilum/arch/_bokeh.py
flokilum/arch/_command.py
flokilum/arch/_dask.py
flokilum/arch/_gdrive.py
flokilum/arch/_help.py
flokilum/arch/_info.py
flokilum/arch/_matplotlib.py
flokilum/arch/_numpy.py
flokilum/arch/_pandas.py
flokilum/arch/_pyarrow.py
flokilum/arch/_shutdown.py
flokilum/arch/_spacy.py
flokilum/arch/_spacy_desm.py
flokilum/arch/_spacy_enlg.py
flokilum/arch/_spacy_enmd.py
flokilum/arch/_spacy_ensm.py
flokilum/arch/_spacy_entr.py
flokilum/arch/_tensorboard.py
flokilum/arch/_torch.py
flokilum/arch/_torchtext.py
flokilum/arch/_torchvision.py
flokilum/colab/__init__.py
flokilum/colab/_bokeh.py
flokilum/colab/_command.py
flokilum/colab/_dask.py
flokilum/colab/_gdrive.py
flokilum/colab/_help.py
flokilum/colab/_info.py
flokilum/colab/_matplotlib.py
flokilum/colab/_numpy.py
flokilum/colab/_pandas.py
flokilum/colab/_pyarrow.py
flokilum/colab/_shutdown.py
flokilum/colab/_spacy.py
flokilum/colab/_spacy_desm.py
flokilum/colab/_spacy_enlg.py
flokilum/colab/_spacy_enmd.py
flokilum/colab/_spacy_ensm.py
flokilum/colab/_spacy_entr.py
flokilum/colab/_tensorboard.py
flokilum/colab/_torch.py
flokilum/colab/_torchtext.py
flokilum/colab/_torchvision.py
flokilum-2021.4.7.dist-info/LICENSE
flokilum-2021.4.7.dist-info/METADATA
flokilum-2021.4.7.dist-info/WHEEL
flokilum-2021.4.7.dist-info/top_level.txt
flokilum-2021.4.7.dist-info/RECORD
