Metadata-Version: 2.1
Name: flokilum
Version: 2021.4.7
Summary: google colab helper
Home-page: https://github.com/pypa/sampleproject
Author: flokilum
Author-email: flokilum@example.com
License: MIT
Platform: UNKNOWN
Classifier: Development Status :: 3 - Alpha
Classifier: License :: OSI Approved :: MIT License
Requires-Python: >=3.6
